sm3md5encoder/__init__.py
sm3md5encoder/encode.py
sm3md5encoder-0.0.2.dist-info/DESCRIPTION.rst
sm3md5encoder-0.0.2.dist-info/METADATA
sm3md5encoder-0.0.2.dist-info/RECORD
sm3md5encoder-0.0.2.dist-info/WHEEL
sm3md5encoder-0.0.2.dist-info/metadata.json
sm3md5encoder-0.0.2.dist-info/top_level.txt
