Metadata-Version: 2.0
Name: sm3md5encoder
Version: 0.0.2
Summary: sm3/md5 encoder
Home-page: UNKNOWN
Author: Yili Peng
Author-email: yili_peng@outlook.com
License: UNKNOWN
Keywords: encoder
Platform: UNKNOWN
